paytm/Checksum.py
paytm/__init__.py
paytm/admin.py
paytm/apps.py
paytm/exceptions.py
paytm/helpers.py
paytm/models.py
paytm/settings.py
paytm/tests.py
paytm/urls.py
paytm/checkout/__init__.py
paytm/checkout/urls.py
paytm/checkout/views.py
paytm/migrations/0001_initial.py
paytm/migrations/0002_auto_20191109_0854.py
paytm/migrations/__init__.py
paytm/templates/paytm/checkout/index.html
paytm/templates/paytm/checkout/redirect.html
paytm/templates/paytm/checkout/status.html
django_paytm_checkout-0.0.3.dist-info/LICENCE
django_paytm_checkout-0.0.3.dist-info/METADATA
django_paytm_checkout-0.0.3.dist-info/WHEEL
django_paytm_checkout-0.0.3.dist-info/top_level.txt
django_paytm_checkout-0.0.3.dist-info/RECORD
