Metadata-Version: 2.1
Name: django-paytm-checkout
Version: 0.0.3
Summary: A simple and modular django app to help with Paytm checkout and custom checkout
Home-page: https://github.com/Faisal-Manzer/django-paytm-checkout
Author: Faisal Manzer
Author-email: faisal_manzer@yahoo.in
License: MIT
Download-URL: https://github.com/Faisal-Manzer/django-paytm-checkout/archive/0.0.1.tar.gz
Platform: UNKNOWN
Classifier: License :: OSI Approved :: MIT License
Classifier: Programming Language :: Python :: 3
Classifier: Programming Language :: Python :: 3.4
Classifier: Programming Language :: Python :: 3.5
Classifier: Programming Language :: Python :: 3.6
Classifier: Programming Language :: Python :: 3.7
Requires-Dist: django
Requires-Dist: djangorestframework
Requires-Dist: pycrypto
